slidize/__init__.py
slidize/_slidize.cp310-win_amd64.pyd
slidize/_slidize.cp311-win_amd64.pyd
slidize/_slidize.cp312-win_amd64.pyd
slidize/_slidize.cp313-win_amd64.pyd
slidize/_slidize.cp35-win_amd64.pyd
slidize/_slidize.cp36-win_amd64.pyd
slidize/_slidize.cp37-win_amd64.pyd
slidize/_slidize.cp38-win_amd64.pyd
slidize/_slidize.cp39-win_amd64.pyd
slidize/pycore.cp310-win_amd64.pyd
slidize/pycore.cp311-win_amd64.pyd
slidize/pycore.cp312-win_amd64.pyd
slidize/pycore.cp313-win_amd64.pyd
slidize/pycore.cp35-win_amd64.pyd
slidize/pycore.cp36-win_amd64.pyd
slidize/pycore.cp37-win_amd64.pyd
slidize/pycore.cp38-win_amd64.pyd
slidize/pycore.cp39-win_amd64.pyd
slidize/pydrawing.cp310-win_amd64.pyd
slidize/pydrawing.cp311-win_amd64.pyd
slidize/pydrawing.cp312-win_amd64.pyd
slidize/pydrawing.cp313-win_amd64.pyd
slidize/pydrawing.cp35-win_amd64.pyd
slidize/pydrawing.cp36-win_amd64.pyd
slidize/pydrawing.cp37-win_amd64.pyd
slidize/pydrawing.cp38-win_amd64.pyd
slidize/pydrawing.cp39-win_amd64.pyd
slidize/pygc.cp310-win_amd64.pyd
slidize/pygc.cp311-win_amd64.pyd
slidize/pygc.cp312-win_amd64.pyd
slidize/pygc.cp313-win_amd64.pyd
slidize/pygc.cp35-win_amd64.pyd
slidize/pygc.cp36-win_amd64.pyd
slidize/pygc.cp37-win_amd64.pyd
slidize/pygc.cp38-win_amd64.pyd
slidize/pygc.cp39-win_amd64.pyd
slidize/pyreflection.cp310-win_amd64.pyd
slidize/pyreflection.cp311-win_amd64.pyd
slidize/pyreflection.cp312-win_amd64.pyd
slidize/pyreflection.cp313-win_amd64.pyd
slidize/pyreflection.cp35-win_amd64.pyd
slidize/pyreflection.cp36-win_amd64.pyd
slidize/pyreflection.cp37-win_amd64.pyd
slidize/pyreflection.cp38-win_amd64.pyd
slidize/pyreflection.cp39-win_amd64.pyd
slidize/__pyinstaller/__init__.pyi
slidize/__pyinstaller/hook-slidize.py
slidize/_slidize/__init__.pyi
slidize/_slidize/__nuitka/__init__.pyi
slidize/_slidize/__nuitka/slidize-_slidize.nuitka-package.config.yml
slidize/_slidize/__pyinstaller/__init__.pyi
slidize/_slidize/__pyinstaller/hook-slidize._slidize.py
slidize_plugins-25.4.0.dist-info/METADATA
slidize_plugins-25.4.0.dist-info/WHEEL
slidize_plugins-25.4.0.dist-info/entry_points.txt
slidize_plugins-25.4.0.dist-info/top_level.txt
slidize_plugins-25.4.0.dist-info/RECORD
