Metadata-Version: 2.1
Name: slidize-plugins
Version: 25.4.0
Summary: Slidize.Plugins is a lightweight Python library for managing presentations and converting them to PowerPoint, OpenDocument, and image formats.
Home-page: https://docs.slidize.com/
Author: Slidize
License: https://about.smallize.com/legal/eula/
Project-URL: Docs, https://docs.slidize.com/
Project-URL: Demos, https://github.com/slidize/slidize-plugins-python
Project-URL: API Reference, https://docs.slidize.com/python/api
Project-URL: Free Support, https://smallize.forumize.com/c/slidize/7
Project-URL: Temporary License, https://www.slidize.com/docs/temp-license.html
Keywords: ppt,pptx,potx,pot,pps,ppsx,odt,import,export,convert,edit,pdf,xps,swf,svg,html,html5,powerpoint,presentation
Platform: win_amd64
Classifier: Intended Audience :: Developers
Classifier: Intended Audience :: Education
Classifier: Intended Audience :: Information Technology
Classifier: License :: Other/Proprietary License
Classifier: License :: Free To Use But Restricted
Classifier: Operating System :: Microsoft :: Windows
Classifier: Operating System :: Unix
Classifier: Operating System :: MacOS
Classifier: Operating System :: POSIX
Classifier: Programming Language :: Python :: 3
Classifier: Programming Language :: Python :: 3 :: Only
Classifier: Programming Language :: Python :: 3.5
Classifier: Programming Language :: Python :: 3.6
Classifier: Programming Language :: Python :: 3.7
Classifier: Programming Language :: Python :: 3.8
Classifier: Programming Language :: Python :: 3.9
Classifier: Programming Language :: Python :: 3.10
Classifier: Programming Language :: Python :: 3.11
Classifier: Programming Language :: Python :: 3.12
Classifier: Programming Language :: Python :: 3.13
Classifier: Topic :: Software Development
Classifier: Topic :: Software Development :: Libraries
Classifier: Topic :: Office/Business
Classifier: Topic :: Office/Business :: Office Suites
Classifier: Topic :: Multimedia :: Graphics :: Presentation
Requires-Python: >=3.5,<3.14
